[
  {
    "block_number": 22293643,
    "node_count": 102,
    "edge_count": 15
  },
  {
    "block_number": 22293642,
    "node_count": 114,
    "edge_count": 43
  },
  {
    "block_number": 22293641,
    "node_count": 112,
    "edge_count": 25
  },
  {
    "block_number": 22293640,
    "node_count": 154,
    "edge_count": 60
  },
  {
    "block_number": 22293639,
    "node_count": 29,
    "edge_count": 0
  },
  {
    "block_number": 22293638,
    "node_count": 41,
    "edge_count": 1
  },
  {
    "block_number": 22293637,
    "node_count": 79,
    "edge_count": 32
  },
  {
    "block_number": 22293636,
    "node_count": 116,
    "edge_count": 20
  },
  {
    "block_number": 22293635,
    "node_count": 37,
    "edge_count": 5
  },
  {
    "block_number": 22293634,
    "node_count": 89,
    "edge_count": 18
  },
  {
    "block_number": 22293633,
    "node_count": 93,
    "edge_count": 25
  },
  {
    "block_number": 22293632,
    "node_count": 78,
    "edge_count": 7
  },
  {
    "block_number": 22293631,
    "node_count": 66,
    "edge_count": 21
  },
  {
    "block_number": 22293630,
    "node_count": 140,
    "edge_count": 19
  },
  {
    "block_number": 22293629,
    "node_count": 32,
    "edge_count": 8
  },
  {
    "block_number": 22293628,
    "node_count": 63,
    "edge_count": 14
  },
  {
    "block_number": 22293627,
    "node_count": 69,
    "edge_count": 13
  },
  {
    "block_number": 22293626,
    "node_count": 98,
    "edge_count": 37
  },
  {
    "block_number": 22293625,
    "node_count": 76,
    "edge_count": 29
  },
  {
    "block_number": 22293624,
    "node_count": 82,
    "edge_count": 20
  },
  {
    "block_number": 22293623,
    "node_count": 57,
    "edge_count": 9
  },
  {
    "block_number": 22293622,
    "node_count": 91,
    "edge_count": 30
  },
  {
    "block_number": 22293621,
    "node_count": 85,
    "edge_count": 23
  },
  {
    "block_number": 22293620,
    "node_count": 122,
    "edge_count": 40
  },
  {
    "block_number": 22293619,
    "node_count": 129,
    "edge_count": 52
  },
  {
    "block_number": 22293618,
    "node_count": 106,
    "edge_count": 29
  },
  {
    "block_number": 22293617,
    "node_count": 33,
    "edge_count": 13
  },
  {
    "block_number": 22293616,
    "node_count": 97,
    "edge_count": 27
  },
  {
    "block_number": 22293615,
    "node_count": 92,
    "edge_count": 14
  },
  {
    "block_number": 22293614,
    "node_count": 93,
    "edge_count": 27
  },
  {
    "block_number": 22293613,
    "node_count": 112,
    "edge_count": 33
  },
  {
    "block_number": 22293612,
    "node_count": 65,
    "edge_count": 15
  },
  {
    "block_number": 22293611,
    "node_count": 102,
    "edge_count": 43
  },
  {
    "block_number": 22293610,
    "node_count": 101,
    "edge_count": 30
  },
  {
    "block_number": 22293609,
    "node_count": 75,
    "edge_count": 15
  },
  {
    "block_number": 22293608,
    "node_count": 90,
    "edge_count": 24
  },
  {
    "block_number": 22293607,
    "node_count": 98,
    "edge_count": 37
  },
  {
    "block_number": 22293606,
    "node_count": 106,
    "edge_count": 31
  },
  {
    "block_number": 22293605,
    "node_count": 49,
    "edge_count": 8
  },
  {
    "block_number": 22293604,
    "node_count": 121,
    "edge_count": 28
  },
  {
    "block_number": 22293603,
    "node_count": 98,
    "edge_count": 40
  },
  {
    "block_number": 22293602,
    "node_count": 59,
    "edge_count": 23
  },
  {
    "block_number": 22293601,
    "node_count": 124,
    "edge_count": 56
  },
  {
    "block_number": 22293600,
    "node_count": 116,
    "edge_count": 59
  },
  {
    "block_number": 22293599,
    "node_count": 130,
    "edge_count": 40
  },
  {
    "block_number": 22293598,
    "node_count": 45,
    "edge_count": 12
  },
  {
    "block_number": 22293597,
    "node_count": 130,
    "edge_count": 56
  },
  {
    "block_number": 22293596,
    "node_count": 74,
    "edge_count": 15
  },
  {
    "block_number": 22293595,
    "node_count": 71,
    "edge_count": 18
  },
  {
    "block_number": 22293594,
    "node_count": 75,
    "edge_count": 14
  },
  {
    "block_number": 22293593,
    "node_count": 79,
    "edge_count": 11
  }
]