[
  {
    "block_number": 22278543,
    "node_count": 79,
    "edge_count": 7
  },
  {
    "block_number": 22278542,
    "node_count": 69,
    "edge_count": 16
  },
  {
    "block_number": 22278541,
    "node_count": 90,
    "edge_count": 18
  },
  {
    "block_number": 22278540,
    "node_count": 73,
    "edge_count": 25
  },
  {
    "block_number": 22278539,
    "node_count": 83,
    "edge_count": 15
  },
  {
    "block_number": 22278538,
    "node_count": 92,
    "edge_count": 28
  },
  {
    "block_number": 22278537,
    "node_count": 147,
    "edge_count": 25
  },
  {
    "block_number": 22278536,
    "node_count": 58,
    "edge_count": 15
  },
  {
    "block_number": 22278535,
    "node_count": 94,
    "edge_count": 16
  },
  {
    "block_number": 22278534,
    "node_count": 79,
    "edge_count": 13
  },
  {
    "block_number": 22278533,
    "node_count": 100,
    "edge_count": 26
  },
  {
    "block_number": 22278532,
    "node_count": 149,
    "edge_count": 57
  },
  {
    "block_number": 22278512,
    "node_count": 62,
    "edge_count": 5
  },
  {
    "block_number": 22278511,
    "node_count": 229,
    "edge_count": 209
  },
  {
    "block_number": 22278510,
    "node_count": 21,
    "edge_count": 0
  },
  {
    "block_number": 22278509,
    "node_count": 121,
    "edge_count": 32
  },
  {
    "block_number": 22278508,
    "node_count": 108,
    "edge_count": 63
  },
  {
    "block_number": 22278507,
    "node_count": 86,
    "edge_count": 42
  },
  {
    "block_number": 22278506,
    "node_count": 136,
    "edge_count": 55
  },
  {
    "block_number": 22278505,
    "node_count": 72,
    "edge_count": 7
  },
  {
    "block_number": 22278504,
    "node_count": 33,
    "edge_count": 23
  },
  {
    "block_number": 22278503,
    "node_count": 105,
    "edge_count": 32
  },
  {
    "block_number": 22278502,
    "node_count": 69,
    "edge_count": 17
  },
  {
    "block_number": 22278501,
    "node_count": 126,
    "edge_count": 38
  },
  {
    "block_number": 22278500,
    "node_count": 83,
    "edge_count": 116
  },
  {
    "block_number": 22278499,
    "node_count": 70,
    "edge_count": 11
  },
  {
    "block_number": 22278498,
    "node_count": 90,
    "edge_count": 30
  },
  {
    "block_number": 22278497,
    "node_count": 124,
    "edge_count": 25
  },
  {
    "block_number": 22278496,
    "node_count": 33,
    "edge_count": 0
  },
  {
    "block_number": 22278495,
    "node_count": 117,
    "edge_count": 25
  },
  {
    "block_number": 22278494,
    "node_count": 113,
    "edge_count": 33
  },
  {
    "block_number": 22278493,
    "node_count": 90,
    "edge_count": 12
  },
  {
    "block_number": 22278492,
    "node_count": 24,
    "edge_count": 3
  },
  {
    "block_number": 22278491,
    "node_count": 122,
    "edge_count": 32
  },
  {
    "block_number": 22278490,
    "node_count": 91,
    "edge_count": 69
  },
  {
    "block_number": 22278489,
    "node_count": 104,
    "edge_count": 21
  },
  {
    "block_number": 22278488,
    "node_count": 117,
    "edge_count": 172
  },
  {
    "block_number": 22278487,
    "node_count": 59,
    "edge_count": 6
  },
  {
    "block_number": 22278486,
    "node_count": 122,
    "edge_count": 23
  },
  {
    "block_number": 22278485,
    "node_count": 18,
    "edge_count": 0
  },
  {
    "block_number": 22278484,
    "node_count": 125,
    "edge_count": 43
  },
  {
    "block_number": 22278483,
    "node_count": 83,
    "edge_count": 21
  },
  {
    "block_number": 22278482,
    "node_count": 89,
    "edge_count": 25
  },
  {
    "block_number": 22278481,
    "node_count": 96,
    "edge_count": 33
  },
  {
    "block_number": 22278480,
    "node_count": 63,
    "edge_count": 11
  },
  {
    "block_number": 22278479,
    "node_count": 135,
    "edge_count": 26
  },
  {
    "block_number": 22278478,
    "node_count": 109,
    "edge_count": 31
  },
  {
    "block_number": 22278477,
    "node_count": 37,
    "edge_count": 3
  },
  {
    "block_number": 22278476,
    "node_count": 63,
    "edge_count": 3
  },
  {
    "block_number": 22278475,
    "node_count": 99,
    "edge_count": 39
  },
  {
    "block_number": 22278474,
    "node_count": 96,
    "edge_count": 19
  }
]