[
  {
    "block_number": 22291091,
    "node_count": 53,
    "edge_count": 9
  },
  {
    "block_number": 22291090,
    "node_count": 146,
    "edge_count": 42
  },
  {
    "block_number": 22291089,
    "node_count": 48,
    "edge_count": 3
  },
  {
    "block_number": 22291088,
    "node_count": 99,
    "edge_count": 20
  },
  {
    "block_number": 22291087,
    "node_count": 110,
    "edge_count": 41
  },
  {
    "block_number": 22291086,
    "node_count": 99,
    "edge_count": 24
  },
  {
    "block_number": 22291085,
    "node_count": 85,
    "edge_count": 19
  },
  {
    "block_number": 22291084,
    "node_count": 110,
    "edge_count": 29
  },
  {
    "block_number": 22291083,
    "node_count": 186,
    "edge_count": 95
  },
  {
    "block_number": 22291082,
    "node_count": 123,
    "edge_count": 66
  },
  {
    "block_number": 22291081,
    "node_count": 135,
    "edge_count": 63
  },
  {
    "block_number": 22291080,
    "node_count": 159,
    "edge_count": 79
  },
  {
    "block_number": 22291079,
    "node_count": 36,
    "edge_count": 15
  },
  {
    "block_number": 22291078,
    "node_count": 151,
    "edge_count": 51
  },
  {
    "block_number": 22291077,
    "node_count": 71,
    "edge_count": 11
  },
  {
    "block_number": 22291076,
    "node_count": 132,
    "edge_count": 32
  },
  {
    "block_number": 22291075,
    "node_count": 117,
    "edge_count": 48
  },
  {
    "block_number": 22291074,
    "node_count": 165,
    "edge_count": 52
  },
  {
    "block_number": 22291073,
    "node_count": 78,
    "edge_count": 18
  },
  {
    "block_number": 22291072,
    "node_count": 110,
    "edge_count": 33
  },
  {
    "block_number": 22291071,
    "node_count": 103,
    "edge_count": 31
  },
  {
    "block_number": 22291070,
    "node_count": 130,
    "edge_count": 40
  },
  {
    "block_number": 22291069,
    "node_count": 82,
    "edge_count": 32
  },
  {
    "block_number": 22291068,
    "node_count": 111,
    "edge_count": 42
  },
  {
    "block_number": 22291067,
    "node_count": 105,
    "edge_count": 32
  },
  {
    "block_number": 22291066,
    "node_count": 98,
    "edge_count": 25
  },
  {
    "block_number": 22291065,
    "node_count": 85,
    "edge_count": 13
  },
  {
    "block_number": 22291064,
    "node_count": 113,
    "edge_count": 44
  },
  {
    "block_number": 22291063,
    "node_count": 112,
    "edge_count": 42
  },
  {
    "block_number": 22291062,
    "node_count": 106,
    "edge_count": 36
  },
  {
    "block_number": 22291061,
    "node_count": 88,
    "edge_count": 29
  },
  {
    "block_number": 22291060,
    "node_count": 119,
    "edge_count": 40
  },
  {
    "block_number": 22291059,
    "node_count": 70,
    "edge_count": 18
  },
  {
    "block_number": 22291058,
    "node_count": 221,
    "edge_count": 123
  },
  {
    "block_number": 22291057,
    "node_count": 78,
    "edge_count": 17
  },
  {
    "block_number": 22291056,
    "node_count": 100,
    "edge_count": 28
  },
  {
    "block_number": 22291055,
    "node_count": 134,
    "edge_count": 49
  },
  {
    "block_number": 22291054,
    "node_count": 129,
    "edge_count": 47
  },
  {
    "block_number": 22291053,
    "node_count": 139,
    "edge_count": 38
  },
  {
    "block_number": 22291052,
    "node_count": 44,
    "edge_count": 5
  },
  {
    "block_number": 22291051,
    "node_count": 159,
    "edge_count": 29
  },
  {
    "block_number": 22291050,
    "node_count": 52,
    "edge_count": 6
  },
  {
    "block_number": 22291049,
    "node_count": 87,
    "edge_count": 25
  },
  {
    "block_number": 22291048,
    "node_count": 98,
    "edge_count": 28
  },
  {
    "block_number": 22291047,
    "node_count": 111,
    "edge_count": 54
  },
  {
    "block_number": 22291046,
    "node_count": 181,
    "edge_count": 64
  },
  {
    "block_number": 22291045,
    "node_count": 96,
    "edge_count": 27
  },
  {
    "block_number": 22291044,
    "node_count": 78,
    "edge_count": 39
  },
  {
    "block_number": 22291043,
    "node_count": 109,
    "edge_count": 32
  },
  {
    "block_number": 22291042,
    "node_count": 78,
    "edge_count": 19
  },
  {
    "block_number": 22291041,
    "node_count": 106,
    "edge_count": 17
  }
]