[
  {
    "block_number": 22289690,
    "node_count": 130,
    "edge_count": 25
  },
  {
    "block_number": 22289689,
    "node_count": 63,
    "edge_count": 5
  },
  {
    "block_number": 22289688,
    "node_count": 128,
    "edge_count": 49
  },
  {
    "block_number": 22289687,
    "node_count": 169,
    "edge_count": 49
  },
  {
    "block_number": 22289686,
    "node_count": 88,
    "edge_count": 22
  },
  {
    "block_number": 22289685,
    "node_count": 122,
    "edge_count": 24
  },
  {
    "block_number": 22289684,
    "node_count": 243,
    "edge_count": 75
  },
  {
    "block_number": 22289683,
    "node_count": 150,
    "edge_count": 39
  },
  {
    "block_number": 22289682,
    "node_count": 24,
    "edge_count": 4
  },
  {
    "block_number": 22289681,
    "node_count": 94,
    "edge_count": 28
  },
  {
    "block_number": 22289680,
    "node_count": 115,
    "edge_count": 27
  },
  {
    "block_number": 22289679,
    "node_count": 92,
    "edge_count": 14
  },
  {
    "block_number": 22289678,
    "node_count": 99,
    "edge_count": 25
  },
  {
    "block_number": 22289677,
    "node_count": 195,
    "edge_count": 39
  },
  {
    "block_number": 22289676,
    "node_count": 70,
    "edge_count": 18
  },
  {
    "block_number": 22289675,
    "node_count": 140,
    "edge_count": 38
  },
  {
    "block_number": 22289674,
    "node_count": 74,
    "edge_count": 3
  },
  {
    "block_number": 22289673,
    "node_count": 138,
    "edge_count": 46
  },
  {
    "block_number": 22289672,
    "node_count": 111,
    "edge_count": 18
  },
  {
    "block_number": 22289671,
    "node_count": 111,
    "edge_count": 29
  },
  {
    "block_number": 22289670,
    "node_count": 158,
    "edge_count": 55
  },
  {
    "block_number": 22289669,
    "node_count": 127,
    "edge_count": 30
  },
  {
    "block_number": 22289668,
    "node_count": 101,
    "edge_count": 14
  },
  {
    "block_number": 22289658,
    "node_count": 145,
    "edge_count": 18
  },
  {
    "block_number": 22289657,
    "node_count": 83,
    "edge_count": 24
  },
  {
    "block_number": 22289656,
    "node_count": 192,
    "edge_count": 77
  },
  {
    "block_number": 22289655,
    "node_count": 114,
    "edge_count": 28
  },
  {
    "block_number": 22289654,
    "node_count": 37,
    "edge_count": 4
  },
  {
    "block_number": 22289653,
    "node_count": 54,
    "edge_count": 9
  },
  {
    "block_number": 22289652,
    "node_count": 160,
    "edge_count": 43
  },
  {
    "block_number": 22289651,
    "node_count": 87,
    "edge_count": 19
  },
  {
    "block_number": 22289650,
    "node_count": 160,
    "edge_count": 60
  },
  {
    "block_number": 22289649,
    "node_count": 101,
    "edge_count": 19
  },
  {
    "block_number": 22289648,
    "node_count": 189,
    "edge_count": 45
  },
  {
    "block_number": 22289647,
    "node_count": 47,
    "edge_count": 5
  },
  {
    "block_number": 22289646,
    "node_count": 260,
    "edge_count": 59
  },
  {
    "block_number": 22289645,
    "node_count": 90,
    "edge_count": 28
  },
  {
    "block_number": 22289644,
    "node_count": 11,
    "edge_count": 3
  },
  {
    "block_number": 22289643,
    "node_count": 104,
    "edge_count": 31
  },
  {
    "block_number": 22289642,
    "node_count": 134,
    "edge_count": 28
  },
  {
    "block_number": 22289641,
    "node_count": 161,
    "edge_count": 36
  },
  {
    "block_number": 22289640,
    "node_count": 81,
    "edge_count": 7
  },
  {
    "block_number": 22289639,
    "node_count": 125,
    "edge_count": 31
  },
  {
    "block_number": 22289638,
    "node_count": 117,
    "edge_count": 24
  },
  {
    "block_number": 22289637,
    "node_count": 109,
    "edge_count": 28
  },
  {
    "block_number": 22289636,
    "node_count": 142,
    "edge_count": 29
  },
  {
    "block_number": 22289635,
    "node_count": 171,
    "edge_count": 49
  },
  {
    "block_number": 22289634,
    "node_count": 69,
    "edge_count": 24
  },
  {
    "block_number": 22289633,
    "node_count": 50,
    "edge_count": 7
  },
  {
    "block_number": 22289632,
    "node_count": 128,
    "edge_count": 28
  },
  {
    "block_number": 22289631,
    "node_count": 129,
    "edge_count": 46
  }
]